{
    "results":  [
                    {
                        "Status":  "Not Connected",
                        "Timestamp":  "2025-02-07T22:00:08",
                        "DisplayName":  "USBC"
                    },
                    {
                        "Status":  "Not Connected",
                        "Timestamp":  "2025-02-07T22:00:08",
                        "DisplayName":  "USBD"
                    },
                    {
                        "Status":  "Not Connected",
                        "Timestamp":  "2025-02-07T22:00:08",
                        "DisplayName":  "USBE"
                    },
                    {
                        "Status":  "Not Connected",
                        "Timestamp":  "2025-02-07T22:00:08",
                        "DisplayName":  "USBF"
                    }
                ]
}
