{
    "results":  [
                    {
                        "Status":  "Connected",
                        "Timestamp":  "2025-03-05T20:45:02",
                        "DisplayName":  "USBC"
                    },
                    {
                        "Status":  "Connected",
                        "Timestamp":  "2025-03-05T20:45:02",
                        "DisplayName":  "USBD"
                    },
                    {
                        "Status":  "Connected",
                        "Timestamp":  "2025-03-05T20:45:02",
                        "DisplayName":  "USBE"
                    },
                    {
                        "Status":  "Not Connected",
                        "Timestamp":  "2025-03-05T20:45:02",
                        "DisplayName":  "USBF"
                    }
                ]
}
